dojocli/__init__.py
dojocli/cli.py
dojocli/docker_client.py
dojocli/dojo_client.py
dojo_cli-0.1.7.dist-info/AUTHORS.md
dojo_cli-0.1.7.dist-info/LICENSE
dojo_cli-0.1.7.dist-info/METADATA
dojo_cli-0.1.7.dist-info/WHEEL
dojo_cli-0.1.7.dist-info/entry_points.txt
dojo_cli-0.1.7.dist-info/top_level.txt
dojo_cli-0.1.7.dist-info/RECORD
