Metadata-Version: 2.1
Name: dojo-cli
Version: 0.1.7
Summary: A command-line interface for black box model execution.
Home-page: https://github.com/dojo-modeling/dojo-cli
Author: Robnet Kerns
Author-email: robnet@jataware.com
License: MIT license
Keywords: dojo-cli
Platform: UNKNOWN
Classifier: Development Status :: 2 - Pre-Alpha
Classifier: Intended Audience :: Developers
Classifier: License :: OSI Approved :: MIT License
Classifier: Natural Language :: English
Classifier: Programming Language :: Python :: 3
Classifier: Programming Language :: Python :: 3.5
Classifier: Programming Language :: Python :: 3.6
Classifier: Programming Language :: Python :: 3.7
Classifier: Programming Language :: Python :: 3.8
Requires-Python: >=3.5
Requires-Dist: Click (<8,>=7.0)
Requires-Dist: Jinja2 (>=2.11.3)
Requires-Dist: docker (>=5.0.3)
Requires-Dist: tqdm (>=4.62.0)
